{"champion":"Vayne","title":"VayneHA","type":"riot","map":"12","mode":"ARAM","priority":false,"blocks":[{"type":"starting","items":[{"id":"1001","count":1},{"id":"1055","count":2},{"id":"2003","count":2}]},{"type":"essential","items":[{"id":"3006","count":1},{"id":"3046","count":1},{"id":"3181","count":1}]},{"type":"offensive","items":[{"id":"3031","count":1},{"id":"3035","count":1},{"id":"3131","count":1}]},{"type":"defensive","items":[{"id":"3139","count":1},{"id":"3102","count":1},{"id":"3022","count":1}]},{"type":"Consumables","items":[{"id":"2003","count":1},{"id":"2004","count":1}]}]}