{
	"champion":"Alistar",
	"title":"Beginner",
	"type":"riot",
	"map":"SR",
	"mode":"INTRO",
	"priority":false,
	"blocks": [
		{"type":"beginner_Starter","maxSummonerLevel":4,"items":[{"id":"1056","count":1}]},
		{"type":"beginner_Starter","minSummonerLevel":5,"items":[{"id":"1056","count":1},{"id":"2003","count":1}]},
		{"type":"beginner_Advanced","recMath":true,"items":[{"id":"1028","count":1},{"id":"1027","count":1},{"id":"3010","count":1}]},
		{"type":"beginner_MovementSpeed","recMath":true,"items":[{"id":"1001","count":1},{"id":"3158","count":1}]},
		{"type":"beginner_LegendaryItem","recMath":true,"items":[{"id":"3010","count":1},{"id":"1026","count":1},{"id":"3027","count":1}]},
		{"type":"beginner_MoreLegendaryItems","items":[{"id":"3065","count":1},{"id":"3110","count":1},{"id":"3001","count":1},{"id":"3083","count":1}]}
]}